{
    "author": null,
    "date_published": null,
    "dek": null,
    "direction": "ltr",
    "domain": "help.twitter.com",
    "excerpt": "Learn about using X.com on older browsers.",
    "lead_image_url": "https://cdn.cms-twdigitalassets.com/content/dam/help-twitter/x/x_sharing_card.png.twimg.768.png",
    "next_page_url": null,
    "rendered_pages": 1,
    "title": "About X.com supported browsers",
    "total_pages": 1,
    "url": "https://help.twitter.com/en/using-x/x-supported-browsers",
    "word_count": 93
}